odoo/addons/ssi_psychology_case_outsource_work/README.rst
odoo/addons/ssi_psychology_case_outsource_work/__init__.py
odoo/addons/ssi_psychology_case_outsource_work/__manifest__.py
odoo/addons/ssi_psychology_case_outsource_work/models/__init__.py
odoo/addons/ssi_psychology_case_outsource_work/models/psychology_case.py
odoo/addons/ssi_psychology_case_outsource_work/static/description/icon.png
odoo14_addon_ssi_psychology_case_outsource_work-14.0.1.2.0.dist-info/METADATA
odoo14_addon_ssi_psychology_case_outsource_work-14.0.1.2.0.dist-info/WHEEL
odoo14_addon_ssi_psychology_case_outsource_work-14.0.1.2.0.dist-info/top_level.txt
odoo14_addon_ssi_psychology_case_outsource_work-14.0.1.2.0.dist-info/RECORD
